activecamp_mcp/__init__.py
activecamp_mcp/analyzers.py
activecamp_mcp/cache.py
activecamp_mcp/content_search.py
activecamp_mcp/exceptions.py
activecamp_mcp/models.py
activecamp_mcp/server.py
activecamp_mcp/settings.py
activecamp_mcp-0.1.0.dist-info/METADATA
activecamp_mcp-0.1.0.dist-info/WHEEL
activecamp_mcp-0.1.0.dist-info/entry_points.txt
activecamp_mcp-0.1.0.dist-info/RECORD
