Metadata-Version: 2.4
Name: activecamp-mcp
Version: 0.1.0
Summary: ActiveCampaign MCP Server
Project-URL: Homepage, https://github.com/kivo360/activecampaign-mcp
Project-URL: Repository, https://github.com/kivo360/activecampaign-mcp
Project-URL: Issues, https://github.com/kivo360/activecampaign-mcp/issues
Author-email: Kevin Hill <kivo360@gmail.com>
License: MIT
Keywords: activecampaign,api,mcp,server
Classifier: Development Status :: 3 - Alpha
Classifier: Intended Audience :: Developers
Classifier: License :: OSI Approved :: MIT License
Classifier: Programming Language :: Python :: 3
Classifier: Programming Language :: Python :: 3.12
Classifier: Topic :: Software Development :: Libraries :: Python Modules
Requires-Python: >=3.12
Requires-Dist: fastmcp>=2.7.0
Requires-Dist: httpx>=0.28.1
Requires-Dist: pydantic-settings>=2.9.1
Requires-Dist: pyyaml>=6.0
